dbmasta/__init__.py
dbmasta/authorization.py
dbmasta/exceptions.py
dbmasta/async_db_client/__init__.py
dbmasta/async_db_client/base.py
dbmasta/async_db_client/engine.py
dbmasta/async_db_client/response.py
dbmasta/async_db_client/tables.py
dbmasta/db_client/__init__.py
dbmasta/db_client/base.py
dbmasta/db_client/response.py
dbmasta/db_client/tables.py
dbmasta/pg_async_client/__init__.py
dbmasta/pg_async_client/base.py
dbmasta/pg_async_client/engine.py
dbmasta/pg_async_client/response.py
dbmasta/pg_async_client/tables.py
dbmasta/pg_client/__init__.py
dbmasta/pg_client/base.py
dbmasta/pg_client/response.py
dbmasta/pg_client/tables.py
dbmasta/response/__init__.py
dbmasta/response/base.py
dbmasta/sql_types/__init__.py
dbmasta/sql_types/sql_types.py
dbmasta/sql_types_pg/__init__.py
dbmasta/sql_types_pg/sql_types.py
dbmasta-0.1.17.dist-info/METADATA
dbmasta-0.1.17.dist-info/WHEEL
dbmasta-0.1.17.dist-info/top_level.txt
dbmasta-0.1.17.dist-info/RECORD
