Metadata-Version: 2.4
Name: dbmasta
Version: 0.1.17
Summary: A simple MariaDB/Postgres client based on SQLAlchemy core
Author-email: Matt Owen <matt@dealerclear.com>
License: MIT
Project-URL: Homepage, https://github.com/mastamatto/dbmasta
Project-URL: Repository, https://github.com/mastamatto/dbmasta
Project-URL: Issues, https://github.com/mastamatto/dbmasta/issues
Classifier: Development Status :: 3 - Alpha
Classifier: Intended Audience :: Developers
Classifier: Topic :: Software Development :: Libraries :: Python Modules
Classifier: License :: OSI Approved :: MIT License
Classifier: Programming Language :: Python :: 3
Classifier: Programming Language :: Python :: 3.7
Classifier: Programming Language :: Python :: 3.8
Classifier: Programming Language :: Python :: 3.9
Classifier: Programming Language :: Python :: 3.10
Classifier: Programming Language :: Python :: 3.11
Classifier: Programming Language :: Python :: 3.12
Classifier: Operating System :: OS Independent
Requires-Python: >=3.7
Requires-Dist: sqlalchemy>=2.0.41
Requires-Dist: aiomysql
Requires-Dist: pymysql
Requires-Dist: asyncpg
Requires-Dist: psycopg-binary
